source_chargebee/__init__.py
source_chargebee/components.py
source_chargebee/manifest.yaml
source_chargebee/run.py
source_chargebee/schemas/addon.json
source_chargebee/schemas/attached_item.json
source_chargebee/schemas/comment.json
source_chargebee/schemas/contact.json
source_chargebee/schemas/coupon.json
source_chargebee/schemas/credit_note.json
source_chargebee/schemas/customer.json
source_chargebee/schemas/differential_price.json
source_chargebee/schemas/event.json
source_chargebee/schemas/gift.json
source_chargebee/schemas/hosted_page.json
source_chargebee/schemas/invoice.json
source_chargebee/schemas/item.json
source_chargebee/schemas/item_family.json
source_chargebee/schemas/item_price.json
source_chargebee/schemas/order.json
source_chargebee/schemas/payment_source.json
source_chargebee/schemas/plan.json
source_chargebee/schemas/promotional_credit.json
source_chargebee/schemas/quote.json
source_chargebee/schemas/quote_line_group.json
source_chargebee/schemas/shared/_definitions.json
source_chargebee/schemas/site_migration_detail.json
source_chargebee/schemas/subscription.json
source_chargebee/schemas/subscription_with_scheduled_changes.json
source_chargebee/schemas/transaction.json
source_chargebee/schemas/unbilled_charge.json
source_chargebee/schemas/virtual_bank_account.json
source_chargebee/source.py
source_chargebee/spec.yaml
airbyte_source_chargebee-0.8.0.dist-info/METADATA
airbyte_source_chargebee-0.8.0.dist-info/WHEEL
airbyte_source_chargebee-0.8.0.dist-info/entry_points.txt
airbyte_source_chargebee-0.8.0.dist-info/RECORD
